tglex/__init__.py
tglex/message.py
tglex/token.py
tglex/tokenize.py
tglex-0.2.1.dist-info/LICENSE
tglex-0.2.1.dist-info/METADATA
tglex-0.2.1.dist-info/WHEEL
tglex-0.2.1.dist-info/top_level.txt
tglex-0.2.1.dist-info/zip-safe
tglex-0.2.1.dist-info/RECORD
